onepattern/__init__.py
onepattern/exceptions.py
onepattern/models/__init__.py
onepattern/models/base.py
onepattern/models/mixins.py
onepattern/py.typed
onepattern/repository/__init__.py
onepattern/repository/alchemy.py
onepattern/schemas/__init__.py
onepattern/schemas/mixins.py
onepattern/schemas/pagination.py
onepattern/settings/__init__.py
onepattern/settings/db.py
onepattern/settings/dsn.py
onepattern/settings/mysql.py
onepattern/settings/pg.py
onepattern/types.py
onepattern/uow/__init__.py
onepattern/uow/abstract.py
onepattern/uow/alchemy.py
onepattern/uow/multiple.py
onepattern/uow/testing.py
onepattern/utils.py
onepattern-0.2.6.dist-info/METADATA
onepattern-0.2.6.dist-info/WHEEL
onepattern-0.2.6.dist-info/RECORD
